LICENSE
README.md
setup.py
test/__init__.py
test/test_conv.py
test/test_layers.py
tfscripts/__about__.py
tfscripts/__init__.py
tfscripts/conv.py
tfscripts/core.py
tfscripts/layers.py
tfscripts/pooling.py
tfscripts/utils.py
tfscripts/weights.py
tfscripts.egg-info/PKG-INFO
tfscripts.egg-info/SOURCES.txt
tfscripts.egg-info/dependency_links.txt
tfscripts.egg-info/requires.txt
tfscripts.egg-info/top_level.txt
tfscripts/compat/__init__.py
tfscripts/compat/v1/__init__.py
tfscripts/compat/v1/conv.py
tfscripts/compat/v1/core.py
tfscripts/compat/v1/layers.py
tfscripts/compat/v1/pooling.py
tfscripts/compat/v1/utils.py
tfscripts/compat/v1/weights.py
tfscripts/compat/v1/hex/__init__.py
tfscripts/compat/v1/hex/conv.py
tfscripts/compat/v1/hex/icecube.py
tfscripts/compat/v1/hex/rotation.py
tfscripts/compat/v1/hex/visual.py
tfscripts/hex/__init__.py
tfscripts/hex/conv.py
tfscripts/hex/icecube.py
tfscripts/hex/rotation.py
tfscripts/hex/visual.py